payler_sdk/__init__.py
payler_sdk/client.py
payler_sdk/exceptions.py
payler_sdk/models.py
payler_sdk/utils.py
payler_sdk-1.0.1.dist-info/licenses/LICENSE
payler_sdk-1.0.1.dist-info/METADATA
payler_sdk-1.0.1.dist-info/WHEEL
payler_sdk-1.0.1.dist-info/top_level.txt
payler_sdk-1.0.1.dist-info/RECORD
